rtvpy/__init__.py
rtvpy/_modidx.py
rtvpy/handle_missingness.py
rtvpy/manipulate.py
rtvpy/modeling.py
rtvpy/variable_decodings.py
rtvpy/wandb_manager.py
rtvpy-0.0.20.dist-info/LICENSE
rtvpy-0.0.20.dist-info/METADATA
rtvpy-0.0.20.dist-info/WHEEL
rtvpy-0.0.20.dist-info/entry_points.txt
rtvpy-0.0.20.dist-info/top_level.txt
rtvpy-0.0.20.dist-info/RECORD
