Metadata-Version: 2.1
Name: rtvpy
Version: 0.0.20
Summary: new python package for data preprocessing
Home-page: https://github.com/Analytics-Raising/rtvpy
Author: jumashafara
Author-email: jumashafara0@gmail.com
License: Apache Software License 2.0
Keywords: nbdev jupyter notebook python
Classifier: Development Status :: 4 - Beta
Classifier: Intended Audience :: Developers
Classifier: Natural Language :: English
Classifier: Programming Language :: Python :: 3.7
Classifier: Programming Language :: Python :: 3.8
Classifier: Programming Language :: Python :: 3.9
Classifier: Programming Language :: Python :: 3.10
Classifier: Programming Language :: Python :: 3.11
Classifier: Programming Language :: Python :: 3.12
Classifier: License :: OSI Approved :: Apache Software License
Requires-Python: >=3.7
License-File: LICENSE
Requires-Dist: pandas
Requires-Dist: wandb
Requires-Dist: python-dotenv
Provides-Extra: dev
